hw_nfr_cs410_pip_test/__init__.py
hw_nfr_cs410_pip_test/feature_mining.py
hw_nfr_cs410_pip_test/hw_nfr_cs410_pip_test.py
hw_nfr_cs410_pip_test-0.0.4.dist-info/LICENSE
hw_nfr_cs410_pip_test-0.0.4.dist-info/METADATA
hw_nfr_cs410_pip_test-0.0.4.dist-info/WHEEL
hw_nfr_cs410_pip_test-0.0.4.dist-info/top_level.txt
hw_nfr_cs410_pip_test-0.0.4.dist-info/RECORD
