Metadata-Version: 2.1
Name: hw-nfr-cs410-pip-test
Version: 0.0.4
Summary: Implicit feature mining
Home-page: https://github.com/nfreundlich/CS410_CourseProject
Author: H.W., N.F
Author-email: norbiein@gmail.com
License: UNKNOWN
Platform: UNKNOWN
Classifier: Programming Language :: Python :: 3
Classifier: License :: OSI Approved :: MIT License
Classifier: Operating System :: OS Independent
